elmarvinflores/__init__.py
elmarvinflores/main.py
elmarvinflores-0.1.0.dist-info/WHEEL
elmarvinflores-0.1.0.dist-info/METADATA
elmarvinflores-0.1.0.dist-info/RECORD
